README.md
setup.py
panda_video/__init__.py
panda_video/wrapper.py
wrapper_panda_video.egg-info/PKG-INFO
wrapper_panda_video.egg-info/SOURCES.txt
wrapper_panda_video.egg-info/dependency_links.txt
wrapper_panda_video.egg-info/requires.txt
wrapper_panda_video.egg-info/top_level.txt