Metadata-Version: 2.1
Name: wrapper-panda-video
Version: 0.0.1
Summary: Wrapper não oficial do Panda Video
Home-page: UNKNOWN
Author: Caio Sampaio
Author-email: caio@pythonando.com.br
License: MIT License
Keywords: panda video
Platform: UNKNOWN
